rpgmva2rpgmmz/classes/tileset.py
rpgmva2rpgmmz/main.py
rpgmva2rpgmmz-0.1.0.dist-info/entry_points.txt
rpgmva2rpgmmz-0.1.0.dist-info/LICENSE
rpgmva2rpgmmz-0.1.0.dist-info/WHEEL
rpgmva2rpgmmz-0.1.0.dist-info/METADATA
rpgmva2rpgmmz-0.1.0.dist-info/RECORD
